wagtailmedia/__init__.py
wagtailmedia/admin.py
wagtailmedia/admin_urls.py
wagtailmedia/apps.py
wagtailmedia/blocks.py
wagtailmedia/deprecation.py
wagtailmedia/edit_handlers.py
wagtailmedia/forms.py
wagtailmedia/models.py
wagtailmedia/permissions.py
wagtailmedia/settings.py
wagtailmedia/signal_handlers.py
wagtailmedia/utils.py
wagtailmedia/wagtail_hooks.py
wagtailmedia/widgets.py
wagtailmedia/api/serializers.py
wagtailmedia/api/views.py
wagtailmedia/locale/.gitkeep
wagtailmedia/locale/de/LC_MESSAGES/django.mo
wagtailmedia/locale/de/LC_MESSAGES/django.po
wagtailmedia/locale/en/LC_MESSAGES/django.mo
wagtailmedia/locale/en/LC_MESSAGES/django.po
wagtailmedia/locale/fr/LC_MESSAGES/django.mo
wagtailmedia/locale/fr/LC_MESSAGES/django.po
wagtailmedia/locale/ro/LC_MESSAGES/django.mo
wagtailmedia/locale/ro/LC_MESSAGES/django.po
wagtailmedia/locale/ru/LC_MESSAGES/django.mo
wagtailmedia/locale/ru/LC_MESSAGES/django.po
wagtailmedia/locale/uk/LC_MESSAGES/django.mo
wagtailmedia/locale/uk/LC_MESSAGES/django.po
wagtailmedia/locale/zh_Hans/LC_MESSAGES/django.mo
wagtailmedia/locale/zh_Hans/LC_MESSAGES/django.po
wagtailmedia/migrations/0001_initial.py
wagtailmedia/migrations/0002_initial_data.py
wagtailmedia/migrations/0003_copy_media_permissions_to_collections.py
wagtailmedia/migrations/0004_duration_optional_floatfield.py
wagtailmedia/migrations/0005_alter_media_options.py
wagtailmedia/migrations/__init__.py
wagtailmedia/static/wagtailmedia/css/wagtailmedia-comparison.css
wagtailmedia/static/wagtailmedia/css/wagtailmedia.css
wagtailmedia/static/wagtailmedia/js/media-chooser-modal.js
wagtailmedia/static/wagtailmedia/js/media-chooser-telepath.js
wagtailmedia/static/wagtailmedia/js/media-chooser.js
wagtailmedia/static/wagtailmedia/js/tabs.js
wagtailmedia/templates/wagtailmedia/chooser/chooser.html
wagtailmedia/templates/wagtailmedia/chooser/results.html
wagtailmedia/templates/wagtailmedia/homepage/site_summary_media.html
wagtailmedia/templates/wagtailmedia/icons/wagtailmedia-audio.svg
wagtailmedia-0.17.2.dist-info/licenses/LICENSE
wagtailmedia-0.17.2.dist-info/WHEEL
wagtailmedia-0.17.2.dist-info/METADATA
wagtailmedia-0.17.2.dist-info/RECORD
