Metadata-Version: 2.4
Name: wagtailmedia
Version: 0.17.2
Summary: A Wagtail module for audio and video files.
Keywords: Wagtail,Django,media
Author-email: Mikalai Radchuk  <hello@torchbox.com>
Maintainer-email: Dan Braghis <dan.braghis@torchbox.com>
Requires-Python: >=3.9
License-Expression: BSD-3-Clause
Classifier: Development Status :: 4 - Beta
Classifier: Environment :: Web Environment
Classifier: Intended Audience :: Developers
Classifier: Operating System :: OS Independent
Classifier: Programming Language :: Python
Classifier: Programming Language :: Python :: 3
Classifier: Programming Language :: Python :: 3.9
Classifier: Programming Language :: Python :: 3.10
Classifier: Programming Language :: Python :: 3.11
Classifier: Programming Language :: Python :: 3.12
Classifier: Programming Language :: Python :: 3.13
Classifier: Framework :: Wagtail
Classifier: Framework :: Wagtail :: 6
Classifier: Framework :: Wagtail :: 7
License-File: LICENSE
Requires-Dist: Wagtail>=6.3
Requires-Dist: Django>=4.2
Requires-Dist: pre-commit>=4.3.0 ; extra == "linting"
Requires-Dist: coverage>=7.10.0 ; extra == "testing"
Requires-Dist: tox>=4.28.4 ; extra == "testing"
Project-URL: Changelog, https://github.com/torchbox/wagtailmedia/blob/main/CHANGELOG.md
Project-URL: Issues, https://github.com/torchbox/wagtailmedia/issues
Project-URL: Repository, https://github.com/torchbox/wagtailmedia
Provides-Extra: linting
Provides-Extra: testing
